robotraconteur_abstract_robot/__init__.py
robotraconteur_abstract_robot/abstract_robot.py
robotraconteur_abstract_robot/joint_trajectory_interpolator.py
robotraconteur_abstract_robot/trapezoidal_joint_trajectory_generator.py
robotraconteur_abstract_robot-0.2.2.dist-info/LICENSE.txt
robotraconteur_abstract_robot-0.2.2.dist-info/METADATA
robotraconteur_abstract_robot-0.2.2.dist-info/WHEEL
robotraconteur_abstract_robot-0.2.2.dist-info/top_level.txt
robotraconteur_abstract_robot-0.2.2.dist-info/RECORD
